gradio_tiff/__init__.py
gradio_tiff/tiff.py
gradio_tiff/tiff.pyi
gradio_tiff/templates/component/index.js
gradio_tiff/templates/component/style.css
gradio_tiff-0.1.2.dist-info/METADATA
gradio_tiff-0.1.2.dist-info/WHEEL
gradio_tiff-0.1.2.dist-info/licenses/LICENSE
gradio_tiff-0.1.2.dist-info/RECORD
