Metadata-Version: 2.4
Name: gradio_tiff
Version: 0.1.2
Summary: Custom Gradio component for multi-page TIFF images
Project-URL: repository, https://github.com/NiklasvonM/Gradio-TIFF/
Project-URL: space, https://huggingface.co/spaces/NiklasvonM/Gradio-TIFF
Author-email: Niklas von Moers <niklasvmoers@protonmail.com>
License-Expression: Apache-2.0
License-File: LICENSE
Keywords: gradio-custom-component,gradio-template-ImageSlider
Classifier: Development Status :: 3 - Alpha
Classifier: Operating System :: OS Independent
Classifier: Programming Language :: Python :: 3
Classifier: Programming Language :: Python :: 3 :: Only
Classifier: Programming Language :: Python :: 3.10
Classifier: Programming Language :: Python :: 3.11
Classifier: Programming Language :: Python :: 3.12
Classifier: Programming Language :: Python :: 3.13
Classifier: Topic :: Scientific/Engineering
Classifier: Topic :: Scientific/Engineering :: Artificial Intelligence
Classifier: Topic :: Scientific/Engineering :: Visualization
Requires-Python: >=3.10
Requires-Dist: gradio<7.0,>=6.0
Provides-Extra: dev
Requires-Dist: build; extra == 'dev'
Requires-Dist: twine; extra == 'dev'
